GHDorker/__init__.py
GHDorker/dorker.py
GHDorker/file_parsing.py
GHDorker/helpers.py
ghdorker-0.3.2.dist-info/LICENSE
ghdorker-0.3.2.dist-info/METADATA
ghdorker-0.3.2.dist-info/WHEEL
ghdorker-0.3.2.dist-info/entry_points.txt
ghdorker-0.3.2.dist-info/top_level.txt
ghdorker-0.3.2.dist-info/RECORD
