Metadata-Version: 2.1
Name: ghdorker
Version: 0.3.2
Summary: A better GitHub Dorking Utility
Home-page: https://github.com/dtaivpp/gh-dorker
Author: David Tippett
License: Apache Software License
Keywords: GitHub Dorker Python Security Dorking
Platform: UNKNOWN
Classifier: Programming Language :: Python :: 3
Classifier: License :: OSI Approved :: Apache Software License
Classifier: Intended Audience :: Developers
Classifier: Operating System :: OS Independent
Requires-Dist: ghapi
Requires-Dist: python-dotenv
Requires-Dist: wheel
